{
  "generatedAt": "2026-06-26T19:50:10.238574+00:00",
  "runs": 5000,
  "assumesCurrentRoster": true,
  "bracketModel": "standings-seeded (v1 approximation)",
  "users": [
    {
      "uid": "KVS3kfS9SYUapdy7rAT7yrYSzT02",
      "name": "Karlos Abel",
      "current": 96,
      "median": 180.0,
      "p20": 156,
      "p80": 207,
      "mean": 182.5,
      "winPct": 24.3,
      "top3Pct": 56.6,
      "teamShare": 37,
      "nTeams": 3,
      "nPlayers": 6,
      "curRank": 1,
      "projRank": 1,
      "rankShift": 0
    },
    {
      "uid": "mniYEjmbmod2SGOgtqG1iPjccRh2",
      "name": "Lisette Bruens",
      "current": 92,
      "median": 165.0,
      "p20": 145,
      "p80": 193,
      "mean": 169.2,
      "winPct": 12.6,
      "top3Pct": 32.6,
      "teamShare": 33,
      "nTeams": 3,
      "nPlayers": 7,
      "curRank": 2,
      "projRank": 2,
      "rankShift": 0
    },
    {
      "uid": "XHZVe2PB3LRGejEg8xjBpsSwGqE2",
      "name": "Carl H",
      "current": 79,
      "median": 160.0,
      "p20": 139,
      "p80": 180,
      "mean": 160.4,
      "winPct": 6.7,
      "top3Pct": 24.1,
      "teamShare": 27,
      "nTeams": 2,
      "nPlayers": 10,
      "curRank": 3,
      "projRank": 3,
      "rankShift": 0
    },
    {
      "uid": "mixdmNZGD3YnzSFOJ077AKfQKXL2",
      "name": "Ronjan Sikdar",
      "current": 73,
      "median": 158.0,
      "p20": 132,
      "p80": 187,
      "mean": 159.8,
      "winPct": 4.9,
      "top3Pct": 24.3,
      "teamShare": 52,
      "nTeams": 5,
      "nPlayers": 5,
      "curRank": 5,
      "projRank": 4,
      "rankShift": 1
    },
    {
      "uid": "u7bzqSV7V9NMD0kGzp4DsqiFbe33",
      "name": "Niraj Patel",
      "current": 71,
      "median": 156.0,
      "p20": 134,
      "p80": 182,
      "mean": 158.1,
      "winPct": 4.4,
      "top3Pct": 18.8,
      "teamShare": 57,
      "nTeams": 6,
      "nPlayers": 6,
      "curRank": 6,
      "projRank": 5,
      "rankShift": 1
    },
    {
      "uid": "HTICTtDMQIVjsLo5hn5UOVfUBO62",
      "name": "Amanda Schneider",
      "current": 74,
      "median": 154.0,
      "p20": 130,
      "p80": 178,
      "mean": 154.7,
      "winPct": 5.4,
      "top3Pct": 21.8,
      "teamShare": 77,
      "nTeams": 8,
      "nPlayers": 2,
      "curRank": 4,
      "projRank": 6,
      "rankShift": -2
    },
    {
      "uid": "8bkCEfWUnENleI0OpbE7VCbCGuf1",
      "name": "Mariss Mednis",
      "current": 68,
      "median": 150.0,
      "p20": 120,
      "p80": 187,
      "mean": 154.7,
      "winPct": 11.5,
      "top3Pct": 24.0,
      "teamShare": 58,
      "nTeams": 6,
      "nPlayers": 5,
      "curRank": 7,
      "projRank": 7,
      "rankShift": 0
    },
    {
      "uid": "wKbTN7lhX8VybKLCQx4UdfE1csm2",
      "name": "Harry Brisson",
      "current": 53,
      "median": 148.0,
      "p20": 125,
      "p80": 171,
      "mean": 148.4,
      "winPct": 3.5,
      "top3Pct": 15.7,
      "teamShare": 100,
      "nTeams": 11,
      "nPlayers": 0,
      "curRank": 12,
      "projRank": 8,
      "rankShift": 4
    },
    {
      "uid": "rVcSCBgxnqZbIkKYLWk6iHSB7LL2",
      "name": "Nick Ransohoff",
      "current": 58,
      "median": 142.0,
      "p20": 121,
      "p80": 165,
      "mean": 142.8,
      "winPct": 2.1,
      "top3Pct": 10.0,
      "teamShare": 100,
      "nTeams": 11,
      "nPlayers": 0,
      "curRank": 9,
      "projRank": 9,
      "rankShift": 0
    },
    {
      "uid": "U4EovkPv7FeYoVYRZpqAxR6CUOo2",
      "name": "Samit Guha",
      "current": 44,
      "median": 138.0,
      "p20": 112,
      "p80": 161,
      "mean": 136.4,
      "winPct": 0.3,
      "top3Pct": 4.2,
      "teamShare": 100,
      "nTeams": 8,
      "nPlayers": 0,
      "curRank": 17,
      "projRank": 10,
      "rankShift": 7
    },
    {
      "uid": "b7kCU3JVSCUixm6QA99bLIu2CKE2",
      "name": "Katherine Kwok",
      "current": 57,
      "median": 138.0,
      "p20": 107,
      "p80": 183,
      "mean": 144.2,
      "winPct": 9.6,
      "top3Pct": 20.8,
      "teamShare": 0,
      "nTeams": 0,
      "nPlayers": 12,
      "curRank": 10,
      "projRank": 11,
      "rankShift": -1
    },
    {
      "uid": "MumnaJM5KNV5B7angaPgEx6yYGt1",
      "name": "Connor Thorpe",
      "current": 58,
      "median": 137.0,
      "p20": 117,
      "p80": 158,
      "mean": 138.1,
      "winPct": 1.9,
      "top3Pct": 6.3,
      "teamShare": 53,
      "nTeams": 6,
      "nPlayers": 6,
      "curRank": 8,
      "projRank": 12,
      "rankShift": -4
    },
    {
      "uid": "M258P797q1YUoHoYfTLlEDNDw9b2",
      "name": "Daniel Ortiz",
      "current": 45,
      "median": 136.0,
      "p20": 113,
      "p80": 158,
      "mean": 135.4,
      "winPct": 0.1,
      "top3Pct": 2.2,
      "teamShare": 100,
      "nTeams": 8,
      "nPlayers": 0,
      "curRank": 15,
      "projRank": 13,
      "rankShift": 2
    },
    {
      "uid": "jy5ChTD9bbYDqcd94VlNKTi4kHV2",
      "name": "Lisa Jordan",
      "current": 54,
      "median": 135.0,
      "p20": 110,
      "p80": 164,
      "mean": 137.2,
      "winPct": 0.9,
      "top3Pct": 4.9,
      "teamShare": 43,
      "nTeams": 3,
      "nPlayers": 6,
      "curRank": 11,
      "projRank": 14,
      "rankShift": -3
    },
    {
      "uid": "UoQrvoSZY8gpncC1w1TEKsoFUWz1",
      "name": "Peter Gallagher",
      "current": 51,
      "median": 132.0,
      "p20": 111,
      "p80": 156,
      "mean": 133.8,
      "winPct": 2.0,
      "top3Pct": 8.5,
      "teamShare": 100,
      "nTeams": 12,
      "nPlayers": 0,
      "curRank": 13,
      "projRank": 15,
      "rankShift": -2
    },
    {
      "uid": "w2UmABKpdKaRJ5FuvNw0iBmKbrf1",
      "name": "Rekhmina Babar",
      "current": 39,
      "median": 131.0,
      "p20": 106,
      "p80": 155,
      "mean": 130.4,
      "winPct": 0.0,
      "top3Pct": 0.5,
      "teamShare": 100,
      "nTeams": 8,
      "nPlayers": 0,
      "curRank": 19,
      "projRank": 16,
      "rankShift": 3
    },
    {
      "uid": "aJJO3KVhiiQ8zOVvgtIrCcB0EUC2",
      "name": "Kelsey Barry",
      "current": 42,
      "median": 129.0,
      "p20": 103,
      "p80": 152,
      "mean": 128.3,
      "winPct": 0.2,
      "top3Pct": 1.6,
      "teamShare": 100,
      "nTeams": 10,
      "nPlayers": 0,
      "curRank": 18,
      "projRank": 17,
      "rankShift": 1
    },
    {
      "uid": "ZqKlu7VT1CTulNg0EDqicXNsacq2",
      "name": "Veronica Hernandez",
      "current": 49,
      "median": 124.0,
      "p20": 102,
      "p80": 146,
      "mean": 124.3,
      "winPct": 1.0,
      "top3Pct": 3.6,
      "teamShare": 100,
      "nTeams": 12,
      "nPlayers": 0,
      "curRank": 14,
      "projRank": 18,
      "rankShift": -4
    },
    {
      "uid": "oiL1RFojGYXiivwwG55CL2Y25Mf2",
      "name": "Maggie Chen",
      "current": 45,
      "median": 123.0,
      "p20": 101,
      "p80": 146,
      "mean": 124.0,
      "winPct": 0.7,
      "top3Pct": 2.7,
      "teamShare": 100,
      "nTeams": 10,
      "nPlayers": 0,
      "curRank": 16,
      "projRank": 19,
      "rankShift": -3
    },
    {
      "uid": "nx4JgoYrM8QyPr6gWQZZhDgQxjm2",
      "name": "Dominic Edwards",
      "current": 34,
      "median": 104.0,
      "p20": 63,
      "p80": 173,
      "mean": 117.6,
      "winPct": 7.8,
      "top3Pct": 16.7,
      "teamShare": 14,
      "nTeams": 1,
      "nPlayers": 10,
      "curRank": 20,
      "projRank": 20,
      "rankShift": 0
    }
  ]
}